saev/__init__.py
saev/__main__.py
saev/activations.py
saev/colors.py
saev/config.py
saev/helpers.py
saev/imaging.py
saev/nn.py
saev/test_activations.py
saev/test_config.py
saev/test_nn.py
saev/test_training.py
saev/test_visuals.py
saev/training.py
saev/visuals.py
saev-0.1.0.dist-info/licenses/LICENSE
saev-0.1.0.dist-info/METADATA
saev-0.1.0.dist-info/WHEEL
saev-0.1.0.dist-info/top_level.txt
saev-0.1.0.dist-info/RECORD
