Metadata-Version: 2.4
Name: saev
Version: 0.1.0
Summary: Sparse autoencoders for vision transformers in PyTorch
Requires-Python: >=3.11
License-File: LICENSE
Requires-Dist: altair>=5.4.1
Requires-Dist: beartype>=0.19.0
Requires-Dist: datasets>=3.0.1
Requires-Dist: einops>=0.8.0
Requires-Dist: jaxtyping>=0.2.34
Requires-Dist: marimo>=0.9.10
Requires-Dist: matplotlib>=3.9.2
Requires-Dist: open-clip-torch>=2.28.0
Requires-Dist: pillow>=10.4.0
Requires-Dist: polars>=1.12.0
Requires-Dist: submitit>=1.5.2
Requires-Dist: torch>=2.5.0
Requires-Dist: tqdm>=4.66.5
Requires-Dist: tyro>=0.8.12
Provides-Extra: classification
Requires-Dist: scipy>=1.15.1; extra == "classification"
Provides-Extra: training
Requires-Dist: wandb>=0.19.6; extra == "training"
Dynamic: license-file
